pacuare/__init__.py
pacuare-0.3.1.dist-info/METADATA
pacuare-0.3.1.dist-info/WHEEL
pacuare-0.3.1.dist-info/RECORD
