Metadata-Version: 2.4
Name: pacuare
Version: 0.3.1
Summary: Query the Pacuare Reserve dataset.
Project-URL: Repository, https://github.com/pacuare/sdk.git
Author-email: Aleks Rūtiņš <keeper@farthergate.com>
License: MIT
Requires-Python: >=3.12
Requires-Dist: pandas<3.0.0,>=2.2.3
Requires-Dist: requests<3.0.0,>=2.32.3
